Abhay_STT/__init__.py
STTAbhay-0.1.dist-info/METADATA
STTAbhay-0.1.dist-info/WHEEL
STTAbhay-0.1.dist-info/top_level.txt
STTAbhay-0.1.dist-info/RECORD
